AUTHORS
ChangeLog
LICENSE
README.md
dim.service
requirements.txt
setup.cfg
setup.py
dim/__init__.py
dim/common.py
dim/display.py
dim/monitor.py
dim.egg-info/PKG-INFO
dim.egg-info/SOURCES.txt
dim.egg-info/dependency_links.txt
dim.egg-info/entry_points.txt
dim.egg-info/not-zip-safe
dim.egg-info/pbr.json
dim.egg-info/requires.txt
dim.egg-info/top_level.txt