Metadata-Version: 1.1
Name: dim
Version: 0.0.1.dev14
Summary: Docker Image Monitor
Home-page: http://github.com/stratoscale/dim.git
Author: Shay Arbov
Author-email: shay.arbov@stratoscale.com
License: UNKNOWN
Platform: UNKNOWN
Classifier: Environment :: Console
Classifier: Intended Audience :: Information Technology
Classifier: Intended Audience :: System Administrators
Classifier: Operating System :: POSIX :: Linux
Classifier: Programming Language :: Python
Classifier: Programming Language :: Python :: 2
Classifier: Programming Language :: Python :: 2.7
